<?xml version = '1.0' encoding = 'UTF-8'?>
<Relation class="oracle.dbtools.crest.model.design.logical.Relation" name="Klasyfikacja" directorySegmentName="seg_0" id="1409A5DF-B7D2-5B21-501A-506E853F0D1B">
<createdBy>mpiot</createdBy>
<createdTime>2022-03-16 19:18:11 UTC</createdTime>
<ownerDesignName>BD2A074</ownerDesignName>
<engineerTo>
<item key="F5E3078B-2D8A-5C7C-C4F5-B5CB4CA9BD19" value="true"/>
</engineerTo>
<targetPk>46C50FCF-2796-655D-28D8-2AE6FAA3CF7F</targetPk>
<identifying>false</identifying>
<nameOnSource>Jest wykonywana przez</nameOnSource>
<nameOnTarget>Wykonuje</nameOnTarget>
<optionalSource>false</optionalSource>
<optionalTarget>true</optionalTarget>
<sourceCardinality>*</sourceCardinality>
<sourceEntity>A378E85D-F36B-88C2-9F82-C001D3272A0D</sourceEntity>
<targetCardinalityString>1</targetCardinalityString>
<targetEntity>C64AB343-7F1C-CBBE-8F40-864DE651C199</targetEntity>
<transferable>true</transferable>
<deleteRule>NO ACTION</deleteRule>
</Relation>